[
    {
        "song_link": "https://music.douban.com/subject/3752947/",
        "img_link": "https://img2.doubanio.com/view/subject/s/public/s3800051.jpg",
        "title": "New Music",
        "raw_info": "X-Ray Dog / 2000 / 专辑 / 数字"
    },
    {
        "song_link": "https://music.douban.com/subject/1418230/",
        "img_link": "https://img1.doubanio.com/view/subject/s/public/s2740208.jpg",
        "title": "惊破梅心",
        "raw_info": "罗守诚 / 1995-03 / 专辑 / CD / 古典"
    },
    {
        "song_link": "https://music.douban.com/subject/2302972/",
        "img_link": "https://img1.doubanio.com/view/subject/s/public/s3166468.jpg",
        "title": "Electrik",
        "raw_info": "马克西姆  Maksim / 2006-10-19 / 专辑 / CD"
    },
    {
        "song_link": "https://music.douban.com/subject/3884032/",
        "img_link": "https://img1.doubanio.com/view/subject/s/public/s3901710.jpg",
        "title": "ゴールデン・ベスト",
        "raw_info": "小林香織 / 2009-03-04 / 选集 / CD / 轻音乐"
    },
    {
        "song_link": "https://music.douban.com/subject/24740874/",
        "img_link": "https://img9.doubanio.com/view/subject/s/public/s29490964.jpg",
        "title": "The Last of Us (Video Game Soundtrack)",
        "raw_info": "Gustavo Santaolalla / 2013-06-11 / 专辑 / Audio CD / 原声"
    },
    {
        "song_link": "https://music.douban.com/subject/1877036/",
        "img_link": "https://img9.doubanio.com/view/subject/s/public/s1812026.jpg",
        "title": "落在淡水的月光",
        "raw_info": "林仁建 / 2004-06 / 专辑 / CD / 轻音乐"
    },
    {
        "song_link": "https://music.douban.com/subject/2073648/",
        "img_link": "https://img3.doubanio.com/view/subject/s/public/s2400552.jpg",
        "title": "MUJI BGM 8",
        "raw_info": "無印良品 / 2005-05-08 / 选集 / CD / 世界音乐"
    },
    {
        "song_link": "https://music.douban.com/subject/26688351/",
        "img_link": "https://img1.doubanio.com/view/subject/s/public/s28363979.jpg",
        "title": "Towards the Light",
        "raw_info": "Jacoo / 2014年07月07日 / 单曲 / 数字(Digital) / 轻音乐"
    },
    {
        "song_link": "https://music.douban.com/subject/10757199/",
        "img_link": "https://img9.doubanio.com/view/subject/s/public/s32270594.jpg",
        "title": "京城四季（一）",
        "raw_info": "何真真 / 2005-12-05 / 专辑 / CD / 轻音乐"
    },
    {
        "song_link": "https://music.douban.com/subject/3163218/",
        "img_link": "https://img3.doubanio.com/view/subject/s/public/s3203997.jpg",
        "title": "H2O - A Solitudes Ambient Experience",
        "raw_info": "Dan Gibson,Chris Phillips / 2008-01-15 / Single / Audio CD / 轻音乐"
    },
    {
        "song_link": "https://music.douban.com/subject/3572822/",
        "img_link": "https://img9.doubanio.com/view/subject/s/public/s3628404.jpg",
        "title": "紫钢琴·君心我心【邓丽君纪念专辑】",
        "raw_info": "全璟璟 / 2008-09-25 / 专辑 / 黑胶CD"
    },
    {
        "song_link": "https://music.douban.com/subject/26829914/",
        "img_link": "https://img3.doubanio.com/view/subject/s/public/s28865507.jpg",
        "title": "Piano Cloud Series - Volume Two",
        "raw_info": "V.A. / 2000 / 专辑 / 数字(Digital) / 轻音乐"
    },
    {
        "song_link": "https://music.douban.com/subject/25699429/",
        "img_link": "https://img2.doubanio.com/view/subject/s/public/s27061361.jpg",
        "title": "WOMAN",
        "raw_info": "松下奈緒 / 2013-10-09 / 专辑 / CD / 流行"
    },
    {
        "song_link": "https://music.douban.com/subject/2131053/",
        "img_link": "https://img1.doubanio.com/view/subject/s/public/s2554618.jpg",
        "title": "Yanni-Tribute",
        "raw_info": "雅尼 / 专辑 / 磁带 / 轻音乐"
    },
    {
        "song_link": "https://music.douban.com/subject/1467513/",
        "img_link": "https://img2.doubanio.com/view/subject/s/public/s1485441.jpg",
        "title": "Ultimate Yanni",
        "raw_info": "Yanni / 2003 / 专辑 / Audio CD / 轻音乐"
    },
    {
        "song_link": "https://music.douban.com/subject/3523710/",
        "img_link": "https://img9.doubanio.com/view/subject/s/public/s3633534.jpg",
        "title": "トライアングル オリジナル・サウンドトラック",
        "raw_info": "澤野弘之,上原ひろみ,林ゆうき / 2009-02-25 / 品番:BVCR-17077 / CD / 原声"
    },
    {
        "song_link": "https://music.douban.com/subject/1418370/",
        "img_link": "https://img1.doubanio.com/view/subject/s/public/s3230169.jpg",
        "title": "The Screen Behind the Mirror",
        "raw_info": "Enigma / 2000 / 专辑 / Audio CD / 电子"
    },
    {
        "song_link": "https://music.douban.com/subject/30311567/",
        "img_link": "https://img9.doubanio.com/view/subject/s/public/s29855204.jpg",
        "title": "乡路",
        "raw_info": "朱家明 / 2018-07-06 / 专辑 / CD"
    },
    {
        "song_link": "https://music.douban.com/subject/20432031/",
        "img_link": "https://img3.doubanio.com/view/subject/s/public/s24477633.jpg",
        "title": "For Now I Am Winter",
        "raw_info": "Ólafur Arnalds / 2013-02-25 / Album / Audio CD / 古典"
    },
    {
        "song_link": "https://music.douban.com/subject/3835049/",
        "img_link": "https://img3.doubanio.com/view/subject/s/public/s3870763.jpg",
        "title": "Great Mystery",
        "raw_info": "Wong Wing Tsan 黄永灿,Hideaki Masago 真砂秀朗 / 2003 / 专辑 / CD"
    }
]