[
    {
        "song_link": "https://music.douban.com/subject/1403832/",
        "img_link": "https://img9.doubanio.com/view/subject/s/public/s4598636.jpg",
        "title": "八度空间",
        "raw_info": "周杰伦 / 2002-07-19 / 专辑 / CD / 流行"
    },
    {
        "song_link": "https://music.douban.com/subject/3592207/",
        "img_link": "https://img3.doubanio.com/view/subject/s/public/s3653823.jpg",
        "title": "茉莉花",
        "raw_info": "中国交响乐团合唱团,中国歌剧舞剧院合唱团 / 2005 / 专辑 / CD / 轻音乐"
    },
    {
        "song_link": "https://music.douban.com/subject/3537123/",
        "img_link": "https://img1.doubanio.com/view/subject/s/public/s3596658.jpg",
        "title": "Number Ones",
        "raw_info": "Michael Jackson / 2003-05-09 / 视频 / DVD / 流行"
    },
    {
        "song_link": "https://music.douban.com/subject/3381873/",
        "img_link": "https://img9.doubanio.com/view/subject/s/public/s3500085.jpg",
        "title": "I Will Always Love You",
        "raw_info": "惠特尼·休斯顿 Whitney Houston / 1992 / EP / Audio CD / 流行"
    },
    {
        "song_link": "https://music.douban.com/subject/2032118/",
        "img_link": "https://img9.doubanio.com/view/subject/s/public/s6894815.jpg",
        "title": "The Sound of Music： 40th Anniversary Special Edition)",
        "raw_info": "Original Soundtrack / 2005-11-08 / 专辑 / CD / 原声"
    },
    {
        "song_link": "https://music.douban.com/subject/1761537/",
        "img_link": "https://img1.doubanio.com/view/subject/s/public/s27232810.jpg",
        "title": "HIStory: Past, Present and Future, Book I",
        "raw_info": "Michael Jackson / 1995 / 专辑 / Audio CD / 流行"
    },
    {
        "song_link": "https://music.douban.com/subject/1411364/",
        "img_link": "https://img3.doubanio.com/view/subject/s/public/s1419273.jpg",
        "title": "张雨生超极品音色精选十六首",
        "raw_info": "张雨生 / 1998 / 选集 / CD / 民谣"
    },
    {
        "song_link": "https://music.douban.com/subject/6838412/",
        "img_link": "https://img9.doubanio.com/view/subject/s/public/s6927365.jpg",
        "title": "红楼梦——87原版电视剧主题歌曲经典回顾珍藏版",
        "raw_info": "陈力,王洁实,王立平 / 2010-09-12 / 专辑 / CD / 原声"
    },
    {
        "song_link": "https://music.douban.com/subject/2287312/",
        "img_link": "https://img9.doubanio.com/view/subject/s/public/s27169414.jpg",
        "title": "继续革命",
        "raw_info": "Beyond / 1992-08 / 专辑 / CD / 摇滚"
    },
    {
        "song_link": "https://music.douban.com/subject/1847490/",
        "img_link": "https://img2.doubanio.com/view/subject/s/public/s3655381.jpg",
        "title": "邓丽君金曲回响演唱会-10亿个掌声",
        "raw_info": "邓丽君 / 视频 / VCD / 流行"
    },
    {
        "song_link": "https://music.douban.com/subject/1781329/",
        "img_link": "https://img9.doubanio.com/view/subject/s/public/s2618006.jpg",
        "title": "The Very Best of Nat King Cole",
        "raw_info": "Nat King Cole / 2006-05-02 / 专辑 / CD / 爵士"
    },
    {
        "song_link": "https://music.douban.com/subject/3447504/",
        "img_link": "https://img2.doubanio.com/view/subject/s/public/s3576431.jpg",
        "title": "哥哥情歌 张国荣",
        "raw_info": "张国荣,張國榮 / 2001-08 / 选集 / CD / 流行"
    },
    {
        "song_link": "https://music.douban.com/subject/1437491/",
        "img_link": "https://img3.doubanio.com/view/subject/s/public/s27311773.jpg",
        "title": "The Best of Simon & Garfunkel",
        "raw_info": "Simon & Garfunkel / 1999-11-16 / Original recording reissued / Original recording remastered / CD / 民谣"
    },
    {
        "song_link": "https://music.douban.com/subject/1428618/",
        "img_link": "https://img1.doubanio.com/view/subject/s/public/s27066220.jpg",
        "title": "真情流露",
        "raw_info": "张学友 / 1992 / 专辑 / CD / 流行"
    },
    {
        "song_link": "https://music.douban.com/subject/1404439/",
        "img_link": "https://img1.doubanio.com/view/subject/s/public/s1413248.jpg",
        "title": "苏武牧羊",
        "raw_info": "李娜 / 1997 / 专辑 / CD / 民谣"
    },
    {
        "song_link": "https://music.douban.com/subject/1402534/",
        "img_link": "https://img9.doubanio.com/view/subject/s/public/s1411386.jpg",
        "title": "Hell Freezes Over",
        "raw_info": "Eagles / 1997-1-1 / 专辑 / CD / 摇滚"
    },
    {
        "song_link": "https://music.douban.com/subject/6548368/",
        "img_link": "https://img3.doubanio.com/view/subject/s/public/s6549283.jpg",
        "title": "歌剧魅影 音乐剧全集",
        "raw_info": "未知艺术家 / 2000 / 专辑 / 数字(Digital) / 轻音乐"
    },
    {
        "song_link": "https://music.douban.com/subject/3579786/",
        "img_link": "https://img1.doubanio.com/view/subject/s/public/s6550810.jpg",
        "title": "吻别",
        "raw_info": "张学友 / 专辑 / CD / 流行"
    },
    {
        "song_link": "https://music.douban.com/subject/2363011/",
        "img_link": "https://img1.doubanio.com/view/subject/s/public/s2830330.jpg",
        "title": "Gold: Greatest Hits",
        "raw_info": "The Carpenters / 2004-04-13 / 专辑 / CD / 民谣"
    },
    {
        "song_link": "https://music.douban.com/subject/1413847/",
        "img_link": "https://img3.doubanio.com/view/subject/s/public/s3651742.jpg",
        "title": "蒋大为",
        "raw_info": "蒋大为 / 2004-1-1 / CD"
    }
]