[
    {
        "song_link": "https://music.douban.com/subject/1406413/",
        "img_link": "https://img3.doubanio.com/view/subject/s/public/s1413912.jpg",
        "title": "世界上最动听的歌",
        "raw_info": "Various Artists / 1999 / 选集 / CD / 摇滚"
    },
    {
        "song_link": "https://music.douban.com/subject/1397751/",
        "img_link": "https://img3.doubanio.com/view/subject/s/public/s1490767.jpg",
        "title": "First Love",
        "raw_info": "宇多田ヒカル / 1999 / 专辑 / CD / 流行"
    },
    {
        "song_link": "https://music.douban.com/subject/6553471/",
        "img_link": "https://img1.doubanio.com/view/subject/s/public/s6558980.jpg",
        "title": "皇后乐队:绝对经典",
        "raw_info": "皇后乐队 / 选集 / CD / 流行"
    },
    {
        "song_link": "https://music.douban.com/subject/6552286/",
        "img_link": "https://img2.doubanio.com/view/subject/s/public/s29883321.jpg",
        "title": "王菲:2010年精选专辑 阿菲正传(3CD)",
        "raw_info": "王菲"
    },
    {
        "song_link": "https://music.douban.com/subject/5382389/",
        "img_link": "https://img9.doubanio.com/view/subject/s/public/s4552994.jpg",
        "title": "OneRepublic",
        "raw_info": "OneRepublic / 2007-11-20 / 专辑 / CD / 流行"
    },
    {
        "song_link": "https://music.douban.com/subject/4740069/",
        "img_link": "https://img1.doubanio.com/view/subject/s/public/s4253269.jpg",
        "title": "李宗盛：再回首",
        "raw_info": "李宗盛 / 2009 / 专辑 / CD / 民谣"
    },
    {
        "song_link": "https://music.douban.com/subject/4563411/",
        "img_link": "https://img3.doubanio.com/view/subject/s/public/s24950252.jpg",
        "title": "岛国之情歌(Vol.1)再见我的爱人",
        "raw_info": "邓丽君 / 1975-09-01 / 专辑 / CD / 流行"
    },
    {
        "song_link": "https://music.douban.com/subject/4241577/",
        "img_link": "https://img2.doubanio.com/view/subject/s/public/s4230711.jpg",
        "title": "上を向いて歩こう",
        "raw_info": "坂本九 / 1961-10-15 / 单曲 / 黑胶"
    },
    {
        "song_link": "https://music.douban.com/subject/3860691/",
        "img_link": "https://img1.doubanio.com/view/subject/s/public/s4673869.jpg",
        "title": "You Are Not Alone",
        "raw_info": "Michael Jackson / 2006-05-30 / Single / Import / Audio CD / 放克/灵歌/R&B"
    },
    {
        "song_link": "https://music.douban.com/subject/3129865/",
        "img_link": "https://img3.doubanio.com/view/subject/s/public/s3159242.jpg",
        "title": "摇太阳",
        "raw_info": "方芳 / 1995 / 专辑 / CD / 流行"
    },
    {
        "song_link": "https://music.douban.com/subject/3024011/",
        "img_link": "https://img3.doubanio.com/view/subject/s/public/s24597237.jpg",
        "title": "平克弗洛伊德:愿你在此",
        "raw_info": "平克弗洛伊德 (Pink Floyd) / 2006 / 专辑 / CD / 摇滚"
    },
    {
        "song_link": "https://music.douban.com/subject/2305621/",
        "img_link": "https://img2.doubanio.com/view/subject/s/public/s2796451.jpg",
        "title": "Spirit: Stallion Of The Cimerron",
        "raw_info": "布莱恩·亚当斯,Bryan Adams / 专辑 / CD / 原声"
    },
    {
        "song_link": "https://music.douban.com/subject/2082502/",
        "img_link": "https://img2.doubanio.com/view/subject/s/public/s1449021.jpg",
        "title": "宠爱",
        "raw_info": "张国荣 / 1995-07-07 / 专辑 / CD / 流行"
    },
    {
        "song_link": "https://music.douban.com/subject/2004349/",
        "img_link": "https://img1.doubanio.com/view/subject/s/public/s2410159.jpg",
        "title": "H.O.T",
        "raw_info": "H.O.T / 2005 / 专辑 / CD"
    },
    {
        "song_link": "https://music.douban.com/subject/1996714/",
        "img_link": "https://img2.doubanio.com/view/subject/s/public/s2157271.jpg",
        "title": "Singin' in the Rain",
        "raw_info": "Various Artists / 1996-06-17 / Soundtrack / CD / 原声"
    },
    {
        "song_link": "https://music.douban.com/subject/1967931/",
        "img_link": "https://img1.doubanio.com/view/subject/s/public/s4459060.jpg",
        "title": "Sweet Child O' Mine",
        "raw_info": "Guns N' Roses / 1988 / CD-single / Special Limited Edition / Import / Audio CD / 摇滚"
    },
    {
        "song_link": "https://music.douban.com/subject/1798950/",
        "img_link": "https://img9.doubanio.com/view/subject/s/public/s3781194.jpg",
        "title": "Mamma Mia!",
        "raw_info": "ABBA / 25 May, 2004 / 专辑 / Audio CD / 原声"
    },
    {
        "song_link": "https://music.douban.com/subject/1485233/",
        "img_link": "https://img9.doubanio.com/view/subject/s/public/s1503064.jpg",
        "title": "丝路",
        "raw_info": "齐秦 / 1996 / 专辑 / CD / 流行"
    },
    {
        "song_link": "https://music.douban.com/subject/1466717/",
        "img_link": "https://img1.doubanio.com/view/subject/s/public/s4641139.jpg",
        "title": "The Definitive Collection",
        "raw_info": "ABBA / 2001 / 选集 / Audio CD / 流行"
    },
    {
        "song_link": "https://music.douban.com/subject/1455270/",
        "img_link": "https://img1.doubanio.com/view/subject/s/public/s2397089.jpg",
        "title": "Creep",
        "raw_info": "Radiohead / 1993 / 单曲 / Audio CD / 摇滚"
    }
]